{
    "ezi_acc_front_1": "500",
    "ezi_acc_front_2": "500",
    "ezi_acc_ready": "500",
    "ezi_acc_rear_1": "500",
    "ezi_acc_rear_2": "500",
    "ezi_acc_rear_3": "500",
    "ezi_acc_turnskleft": "500",
    "ezi_acc_turnskright": "500",
    "ezi_dec_front_1": "500",
    "ezi_dec_front_2": "500",
    "ezi_dec_ready": "500",
    "ezi_dec_rear_1": "500",
    "ezi_dec_rear_2": "500",
    "ezi_dec_rear_3": "500",
    "ezi_dec_turnskleft": "500",
    "ezi_dec_turnskright": "500",
    "ezi_pos_front_1_x": "8738",
    "ezi_pos_front_1_y": "-1589",
    "ezi_pos_front_2_x": "8738",
    "ezi_pos_front_2_y": "-1589",
    "ezi_pos_ready_x": "2219",
    "ezi_pos_ready_y": "4272",
    "ezi_pos_rear_1_x": "10803",
    "ezi_pos_rear_1_y": "-2146",
    "ezi_pos_rear_2_x": "10803",
    "ezi_pos_rear_2_y": "-3508",
    "ezi_pos_rear_3_x": "9848",
    "ezi_pos_rear_3_y": "-3481",
    "ezi_pos_turnskleft_x": "-3896",
    "ezi_pos_turnskleft_y": "-6277",
    "ezi_pos_turnskright_x": "8878",
    "ezi_pos_turnskright_y": "-6277",
    "ezi_vel_front_1": "50000",
    "ezi_vel_front_2": "50000",
    "ezi_vel_ready": "50000",
    "ezi_vel_rear_1": "50000",
    "ezi_vel_rear_2": "50000",
    "ezi_vel_rear_3": "50000",
    "ezi_vel_turnskleft": "50000",
    "ezi_vel_turnskright": "50000",
	"ezi_pos_rear_4_x": "0",
    "ezi_pos_rear_4_y": "0",
    "ezi_vel_rear_4": "0",
    "ezi_acc_rear_4": "0",
    "ezi_dec_rear_4": "0"
}
